Code1v1/__init__.py
Code1v1/__version__.py
Code1v1/chapter1/ClassGame.py
Code1v1/chapter1/__init__.py
chapter1/__init__.py
chapter1/__version__.py
chapter1/core.py
Code1v1-0.0.8.dist-info/LICENSE
Code1v1-0.0.8.dist-info/METADATA
Code1v1-0.0.8.dist-info/WHEEL
Code1v1-0.0.8.dist-info/top_level.txt
Code1v1-0.0.8.dist-info/RECORD
