Metadata-Version: 2.1
Name: Code1v1
Version: 0.0.8
Summary: Code 1v1 是 AI悦创·致力推广编程教学而研发的教学库
Home-page: https://github.com/AndersonHJB/Code1v1
Author: Bornforthis
Author-email: bornforthis@bornforthis.cn
License: MIT
Platform: UNKNOWN
Classifier: License :: OSI Approved :: MIT License
Classifier: Programming Language :: Python
Classifier: Programming Language :: Python :: 3
Classifier: Programming Language :: Python :: 3.6
Classifier: Programming Language :: Python :: Implementation :: CPython
Classifier: Programming Language :: Python :: Implementation :: PyPy
Requires-Python: >=3.6.0
License-File: LICENSE
